__init__.py
demeter/__init__.py
demeter/constants.py
demeter/metamorphosis/__init__.py
demeter/metamorphosis/abstract.py
demeter/metamorphosis/classic.py
demeter/metamorphosis/constrained.py
demeter/metamorphosis/data_cost.py
demeter/metamorphosis/joined.py
demeter/metamorphosis/load.py
demeter/metamorphosis/simplex.py
demeter/metamorphosis/wraps.py
demeter/utils/__init__.py
demeter/utils/bspline.py
demeter/utils/cost_functions.py
demeter/utils/decorators.py
demeter/utils/fft_conv.py
demeter/utils/fill_saves_overview.py
demeter/utils/image_3d_plotter.py
demeter/utils/image_3d_visu_vedo.py
demeter/utils/optim.py
demeter/utils/reproducing_kernels.py
demeter/utils/toolbox.py
demeter/utils/torchbox.py
demeter/utils/vector_field_to_flow.py
demeter_metamorphosis-0.2.11.dist-info/METADATA
demeter_metamorphosis-0.2.11.dist-info/WHEEL
demeter_metamorphosis-0.2.11.dist-info/top_level.txt
demeter_metamorphosis-0.2.11.dist-info/RECORD
