Metadata-Version: 2.4
Name: demeter_metamorphosis
Version: 0.2.11
Summary: Efficient and flexible optimization of metamorphoses in images
Author-email: Anton François <anton.francois@ens-paris-saclay.fr>
License: MIT
Project-URL: Homepage, https://github.com/antonfrancois/demeter_metamorphosis
Project-URL: Documentation, https://demeter_metamorphosis.readthedocs.io
Classifier: Development Status :: 3 - Alpha
Classifier: Intended Audience :: Developers
Classifier: License :: OSI Approved :: MIT License
Classifier: Programming Language :: Python :: 3.12
Requires-Python: >=3.11
Requires-Dist: torch>=2.4.1
Requires-Dist: matplotlib>=3.3.2
Requires-Dist: sphinx>=4.0.2
Requires-Dist: sphinx-gallery>=0.9.0
Requires-Dist: numpy==1.26.4; python_version < "3.12"
Requires-Dist: tensorflow==2.18.0; python_version < "3.12"
Requires-Dist: numpy==2.2.0; python_version >= "3.12"
Requires-Dist: scikit_image==0.25.0
Requires-Dist: kornia==0.7.1
Requires-Dist: pytest
Requires-Dist: icecream
Requires-Dist: nibabel
Requires-Dist: napari
Requires-Dist: dotenv
Provides-Extra: img-basics
Requires-Dist: scipy; extra == "img-basics"
Requires-Dist: nibabel; extra == "img-basics"
Requires-Dist: napari; extra == "img-basics"
Requires-Dist: nrrd; extra == "img-basics"
Requires-Dist: icecream; extra == "img-basics"
